pygame_animatedgif/__init__.py
pygame_animatedgif-0.1.0.dist-info/LICENSE
pygame_animatedgif-0.1.0.dist-info/METADATA
pygame_animatedgif-0.1.0.dist-info/WHEEL
pygame_animatedgif-0.1.0.dist-info/top_level.txt
pygame_animatedgif-0.1.0.dist-info/RECORD
