Metadata-Version: 2.1
Name: pygame-animatedgif
Version: 0.1.0
Summary: A sprite based PyGame class to use animated GIFs
Home-page: https://github.com/Jokymon/GIFImage_ext
Author: Silvan Wegmann
Author-email: pygame_animatedgif@narf.ch
License: UNKNOWN
Platform: UNKNOWN
Classifier: License :: CC0 1.0 Universal (CC0 1.0) Public Domain Dedication
Classifier: Programming Language :: Python :: 3
Classifier: Operating System :: OS Independent
Classifier: Topic :: Software Development :: Libraries :: pygame
License-File: LICENSE
Requires-Dist: pygame
Requires-Dist: Pillow
